{"textures":{"0":"item/mobs/zaku/zaku"},"elements":[{"from":[4.703514,14.470348,6.424897],"to":[5.4877424,15.254578,10.34604],"rotation":{"angle":-45.0,"axis":"y","origin":[7.9826684,14.746566,8.135589]},"faces":{"east":{"uv":[2.5,1.5,3.75,1.75],"rotation":0,"texture":"#0","tintindex":0},"south":{"uv":[4.5,2.5,4.75,2.75],"rotation":0,"texture":"#0","tintindex":0},"north":{"uv":[0.5,4.5,0.75,4.75],"rotation":0,"texture":"#0","tintindex":0},"west":{"uv":[2.5,1.75,3.75,2.0],"rotation":0,"texture":"#0","tintindex":0},"up":{"uv":[2.0,4.0,1.75,2.75],"rotation":0,"texture":"#0","tintindex":0},"down":{"uv":[2.25,2.75,2.0,4.0],"rotation":0,"texture":"#0","tintindex":0}}},{"from":[8.124914,13.686121,9.561806],"to":[8.9091425,14.470348,10.346034],"rotation":{"angle":45.0,"axis":"y","origin":[7.9826684,14.746566,8.135589]},"faces":{"east":{"uv":[3.75,4.75,3.5,5.0],"rotation":0,"texture":"#0","tintindex":0},"south":{"uv":[3.5,4.75,3.25,5.0],"rotation":0,"texture":"#0","tintindex":0},"north":{"uv":[5.0,2.5,4.75,2.75],"rotation":0,"texture":"#0","tintindex":0},"west":{"uv":[5.0,2.75,4.75,3.0],"rotation":0,"texture":"#0","tintindex":0},"up":{"uv":[4.75,3.75,5.0,3.5],"rotation":0,"texture":"#0","tintindex":0},"down":{"uv":[3.75,4.75,4.0,5.0],"rotation":0,"texture":"#0","tintindex":0}}},{"from":[9.408886,14.470348,5.6406627],"to":[10.193114,15.254578,7.9933486],"rotation":{"angle":-45.0,"axis":"y","origin":[7.9826684,14.746566,8.135589]},"faces":{"east":{"uv":[5.0,2.0,4.25,2.25],"rotation":0,"texture":"#0","tintindex":0},"south":{"uv":[5.0,0.25,4.75,0.5],"rotation":0,"texture":"#0","tintindex":0},"north":{"uv":[5.0,0.0,4.75,0.25],"rotation":0,"texture":"#0","tintindex":0},"west":{"uv":[4.75,1.25,4.0,1.5],"rotation":0,"texture":"#0","tintindex":0},"up":{"uv":[1.5,5.0,1.75,4.25],"rotation":0,"texture":"#0","tintindex":0},"down":{"uv":[4.25,2.25,4.5,3.0],"rotation":0,"texture":"#0","tintindex":0}}},{"from":[10.477594,12.117663,6.424897],"to":[11.261823,14.470348,7.2091255],"rotation":{"angle":45.0,"axis":"y","origin":[7.9826684,14.746566,8.135589]},"faces":{"east":{"uv":[1.5,4.25,1.25,5.0],"rotation":0,"texture":"#0","tintindex":0},"south":{"uv":[4.25,4.0,4.0,4.75],"rotation":0,"texture":"#0","tintindex":0},"north":{"uv":[3.75,4.0,3.5,4.75],"rotation":0,"texture":"#0","tintindex":0},"west":{"uv":[4.0,4.0,3.75,4.75],"rotation":0,"texture":"#0","tintindex":0},"up":{"uv":[4.5,4.5,4.75,4.25],"rotation":0,"texture":"#0","tintindex":0},"down":{"uv":[4.5,4.5,4.75,4.75],"rotation":0,"texture":"#0","tintindex":0}}},{"from":[10.477594,14.470348,6.424897],"to":[11.261823,15.254578,10.34604],"rotation":{"angle":45.0,"axis":"y","origin":[7.9826684,14.746566,8.135589]},"faces":{"east":{"uv":[3.75,1.75,2.5,2.0],"rotation":0,"texture":"#0","tintindex":0},"south":{"uv":[4.75,2.5,4.5,2.75],"rotation":0,"texture":"#0","tintindex":0},"north":{"uv":[0.75,4.5,0.5,4.75],"rotation":0,"texture":"#0","tintindex":0},"west":{"uv":[3.75,1.5,2.5,1.75],"rotation":0,"texture":"#0","tintindex":0},"up":{"uv":[1.75,4.0,2.0,2.75],"rotation":0,"texture":"#0","tintindex":0},"down":{"uv":[2.0,2.75,2.25,4.0],"rotation":0,"texture":"#0","tintindex":0}}},{"from":[5.4877424,13.686121,5.6406684],"to":[9.408886,17.607264,9.561811],"rotation":{"angle":-45.0,"axis":"y","origin":[7.9826684,14.746566,8.135589]},"faces":{"east":{"uv":[0.0,1.25,1.25,2.5],"rotation":0,"texture":"#0","tintindex":0},"south":{"uv":[1.25,1.25,0.0,2.5],"rotation":0,"texture":"#0","tintindex":0},"north":{"uv":[2.5,1.25,1.25,2.5],"rotation":0,"texture":"#0","tintindex":0},"west":{"uv":[1.25,1.25,2.5,2.5],"rotation":0,"texture":"#0","tintindex":0},"up":{"uv":[1.25,3.75,0.0,2.5],"rotation":0,"texture":"#0","tintindex":0},"down":{"uv":[3.75,0.0,2.5,1.25],"rotation":0,"texture":"#0","tintindex":0}}},{"from":[4.703514,12.117663,6.424897],"to":[5.4877424,14.470348,7.2091255],"rotation":{"angle":-45.0,"axis":"y","origin":[7.9826684,14.746566,8.135589]},"faces":{"east":{"uv":[3.75,4.0,4.0,4.75],"rotation":0,"texture":"#0","tintindex":0},"south":{"uv":[4.0,4.0,4.25,4.75],"rotation":0,"texture":"#0","tintindex":0},"north":{"uv":[3.5,4.0,3.75,4.75],"rotation":0,"texture":"#0","tintindex":0},"west":{"uv":[1.25,4.25,1.5,5.0],"rotation":0,"texture":"#0","tintindex":0},"up":{"uv":[4.75,4.5,4.5,4.25],"rotation":0,"texture":"#0","tintindex":0},"down":{"uv":[4.75,4.5,4.5,4.75],"rotation":0,"texture":"#0","tintindex":0}}},{"from":[5.7722225,14.470348,5.6406627],"to":[6.5564513,15.254578,7.9933486],"rotation":{"angle":45.0,"axis":"y","origin":[7.9826684,14.746566,8.135589]},"faces":{"east":{"uv":[4.0,1.25,4.75,1.5],"rotation":0,"texture":"#0","tintindex":0},"south":{"uv":[4.75,0.25,5.0,0.5],"rotation":0,"texture":"#0","tintindex":0},"north":{"uv":[4.75,0.0,5.0,0.25],"rotation":0,"texture":"#0","tintindex":0},"west":{"uv":[4.25,2.0,5.0,2.25],"rotation":0,"texture":"#0","tintindex":0},"up":{"uv":[1.75,5.0,1.5,4.25],"rotation":0,"texture":"#0","tintindex":0},"down":{"uv":[4.5,2.25,4.25,3.0],"rotation":0,"texture":"#0","tintindex":0}}},{"from":[5.4877424,12.901892,5.6406684],"to":[7.0562,13.686121,7.2091255],"rotation":{"angle":-45.0,"axis":"y","origin":[7.9826684,14.746566,8.135589]},"faces":{"east":{"uv":[1.75,4.5,2.25,4.75],"rotation":0,"texture":"#0","tintindex":0},"south":{"uv":[2.25,4.5,2.75,4.75],"rotation":0,"texture":"#0","tintindex":0},"north":{"uv":[4.5,1.0,5.0,1.25],"rotation":0,"texture":"#0","tintindex":0},"west":{"uv":[4.5,2.25,5.0,2.5],"rotation":0,"texture":"#0","tintindex":0},"up":{"uv":[3.75,3.5,3.25,3.0],"rotation":0,"texture":"#0","tintindex":0},"down":{"uv":[3.75,3.5,3.25,4.0],"rotation":0,"texture":"#0","tintindex":0}}},{"from":[9.408886,16.038807,5.6406627],"to":[10.193114,16.823034,9.561806],"rotation":{"angle":-45.0,"axis":"y","origin":[7.9826684,14.746566,8.135589]},"faces":{"east":{"uv":[2.75,2.5,4.0,2.75],"rotation":0,"texture":"#0","tintindex":0},"south":{"uv":[4.75,1.25,5.0,1.5],"rotation":0,"texture":"#0","tintindex":0},"north":{"uv":[1.0,4.75,1.25,5.0],"rotation":0,"texture":"#0","tintindex":0},"west":{"uv":[2.75,2.75,4.0,3.0],"rotation":0,"texture":"#0","tintindex":0},"up":{"uv":[3.0,4.25,2.75,3.0],"rotation":0,"texture":"#0","tintindex":0},"down":{"uv":[3.25,3.0,3.0,4.25],"rotation":0,"texture":"#0","tintindex":0}}},{"from":[5.7722225,16.038807,5.6406627],"to":[6.5564513,16.823034,10.346034],"rotation":{"angle":45.0,"axis":"y","origin":[7.9826684,14.746566,8.135589]},"faces":{"east":{"uv":[1.25,2.5,2.75,2.75],"rotation":0,"texture":"#0","tintindex":0},"south":{"uv":[1.75,4.75,2.0,5.0],"rotation":0,"texture":"#0","tintindex":0},"north":{"uv":[4.75,1.5,5.0,1.75],"rotation":0,"texture":"#0","tintindex":0},"west":{"uv":[2.5,1.25,4.0,1.5],"rotation":0,"texture":"#0","tintindex":0},"up":{"uv":[1.5,4.25,1.25,2.75],"rotation":0,"texture":"#0","tintindex":0},"down":{"uv":[1.75,2.75,1.5,4.25],"rotation":0,"texture":"#0","tintindex":0}}},{"from":[4.703514,16.038807,7.2091255],"to":[5.4877424,16.823034,10.34604],"rotation":{"angle":-45.0,"axis":"y","origin":[7.9826684,14.746566,8.135589]},"faces":{"east":{"uv":[3.75,1.5,4.75,1.75],"rotation":0,"texture":"#0","tintindex":0},"south":{"uv":[2.0,4.75,2.25,5.0],"rotation":0,"texture":"#0","tintindex":0},"north":{"uv":[4.75,1.75,5.0,2.0],"rotation":0,"texture":"#0","tintindex":0},"west":{"uv":[3.75,1.75,4.75,2.0],"rotation":0,"texture":"#0","tintindex":0},"up":{"uv":[4.0,4.0,3.75,3.0],"rotation":0,"texture":"#0","tintindex":0},"down":{"uv":[0.25,4.0,0.0,5.0],"rotation":0,"texture":"#0","tintindex":0}}},{"from":[10.477594,16.038807,7.2091255],"to":[11.261823,16.823034,10.34604],"rotation":{"angle":45.0,"axis":"y","origin":[7.9826684,14.746566,8.135589]},"faces":{"east":{"uv":[4.75,1.75,3.75,2.0],"rotation":0,"texture":"#0","tintindex":0},"south":{"uv":[2.25,4.75,2.0,5.0],"rotation":0,"texture":"#0","tintindex":0},"north":{"uv":[5.0,1.75,4.75,2.0],"rotation":0,"texture":"#0","tintindex":0},"west":{"uv":[4.75,1.5,3.75,1.75],"rotation":0,"texture":"#0","tintindex":0},"up":{"uv":[3.75,4.0,4.0,3.0],"rotation":0,"texture":"#0","tintindex":0},"down":{"uv":[0.0,4.0,0.25,5.0],"rotation":0,"texture":"#0","tintindex":0}}},{"from":[7.19844,17.97171,7.172],"to":[8.766897,19.540165,8.740458],"rotation":{"angle":-45.0,"axis":"x","origin":[7.9826684,15.03228,8.135589]},"faces":{"east":{"uv":[0.25,4.0,0.75,4.5],"rotation":0,"texture":"#0","tintindex":0},"south":{"uv":[4.0,0.25,4.5,0.75],"rotation":0,"texture":"#0","tintindex":0},"north":{"uv":[3.75,2.0,4.25,2.5],"rotation":0,"texture":"#0","tintindex":0},"west":{"uv":[4.0,0.75,4.5,1.25],"rotation":0,"texture":"#0","tintindex":0},"up":{"uv":[2.25,4.5,1.75,4.0],"rotation":0,"texture":"#0","tintindex":0},"down":{"uv":[2.75,4.0,2.25,4.5],"rotation":0,"texture":"#0","tintindex":0}}},{"from":[7.4925256,18.854555,5.8907886],"to":[8.472812,21.77867,6.871074],"rotation":{"angle":-22.5,"axis":"x","origin":[7.9826684,15.03228,8.135589]},"faces":{"east":{"uv":[4.25,4.25,4.5,5.0],"rotation":0,"texture":"#0","tintindex":0},"south":{"uv":[0.25,4.5,0.5,5.25],"rotation":0,"texture":"#0","tintindex":0},"north":{"uv":[4.25,3.5,4.5,4.25],"rotation":0,"texture":"#0","tintindex":0},"west":{"uv":[4.5,0.25,4.75,1.0],"rotation":0,"texture":"#0","tintindex":0},"up":{"uv":[2.5,5.0,2.25,4.75],"rotation":0,"texture":"#0","tintindex":0},"down":{"uv":[2.75,4.75,2.5,5.0],"rotation":0,"texture":"#0","tintindex":0}}},{"from":[7.0561943,13.686121,9.561806],"to":[7.8404226,14.470348,10.346034],"rotation":{"angle":-45.0,"axis":"y","origin":[7.9826684,14.746566,8.135589]},"faces":{"east":{"uv":[4.75,2.75,5.0,3.0],"rotation":0,"texture":"#0","tintindex":0},"south":{"uv":[3.25,4.75,3.5,5.0],"rotation":0,"texture":"#0","tintindex":0},"north":{"uv":[4.75,2.5,5.0,2.75],"rotation":0,"texture":"#0","tintindex":0},"west":{"uv":[3.5,4.75,3.75,5.0],"rotation":0,"texture":"#0","tintindex":0},"up":{"uv":[5.0,3.75,4.75,3.5],"rotation":0,"texture":"#0","tintindex":0},"down":{"uv":[4.0,4.75,3.75,5.0],"rotation":0,"texture":"#0","tintindex":0}}}],"display":{"head":{"translation":[0.0,-6.4,0.0],"scale":[4.0,4.0,4.0]}}}